et_auto_build/__init__.py
et_auto_build/cpp_bar/CMakeLists.txt
et_auto_build/cpp_bar/bar.cpp
et_auto_build/cpp_bar/bar.rst
et_auto_build/f2py_foo/foo.f90
et_auto_build/f2py_foo/foo.rst
et_auto_build-0.0.0.dist-info/entry_points.txt
et_auto_build-0.0.0.dist-info/LICENSE
et_auto_build-0.0.0.dist-info/WHEEL
et_auto_build-0.0.0.dist-info/METADATA
et_auto_build-0.0.0.dist-info/RECORD
