Metadata-Version: 2.1
Name: et-auto-build
Version: 0.0.0
Summary: <Enter a one-sentence description of this project here.>
Home-page: https://github.com/etijskens/et-auto-build
License: MIT
Keywords: packaging,poetry
Author: Engelbert Tijskens
Author-email: engelbert.tijskens@uantwerpen.be
Requires-Python: >=3.7,<4.0
Classifier: License :: OSI Approved :: MIT License
Classifier: Programming Language :: Python :: 3
Classifier: Programming Language :: Python :: 3.7
Classifier: Programming Language :: Python :: 3.8
Requires-Dist: et-micc-build (>=0.9.41,<0.10.0)
Project-URL: Repository, https://github.com/etijskens/et-auto-build
